Metadata-Version: 2.1
Name: factura-com-library
Version: 0.0.4
Summary: Librería para consumir la API de factura.com para generar facturas fiscales en México.
Home-page: https://github.com/Lexharden
Author: Alexis Yafel Garcia
Author-email: a.yafel10@gmail.com
License: MIT
Keywords: factura,factura.com,API,facturación electrónica,México,CFDI,Timbrado
Classifier: Development Status :: 3 - Alpha
Classifier: Intended Audience :: Developers
Classifier: License :: OSI Approved :: MIT License
Classifier: Programming Language :: Python :: 3
Classifier: Programming Language :: Python :: 3.9
Classifier: Topic :: Software Development :: Libraries :: Python Modules
Requires-Dist: certifi ==2024.2.2
Requires-Dist: charset-normalizer ==3.3.2
Requires-Dist: idna ==3.6
Requires-Dist: requests ==2.31.0
Requires-Dist: urllib3 ==2.2.1
